{"type":"FeatureCollection",
"features":[
    {
        "type":"Feature",
        "properties":{
            "place":"Greece: only place in Europe that I've travelled to",
            "color": "purple"
            },
            "geometry":{
                "coordinates":[
                    21.562455958820436,39.21502827123331
                    ],
                    "type":"Point"
                    }
                    },
                    {"type":"Feature",
                    "properties":{
                        "place": "Spain: #1 on my travel list",
                        "color": "red"
                        },"geometry":{
                            "coordinates":[-3.3195729226184483,41.23984922862206],"type":"Point"}},{"type":"Feature","properties":{"place": "France: can't wait to eat nutella crepes here!", "color": "orange"},"geometry":{"coordinates":[2.9265222820443455,49.25284127672279],"type":"Point"}},{"type":"Feature","properties":{"place": "Russia: visit for New Year's", "color": "blue"},"geometry":{"coordinates":[71.97406473243143,60.06261073217058],"type":"Point"}}]}